kaiterra_async_client/__init__.py
kaiterra_async_client/client.py
kaiterra_async_client/dateutil.py
kaiterra_async_client-1.1.0.dist-info/LICENSE
kaiterra_async_client-1.1.0.dist-info/METADATA
kaiterra_async_client-1.1.0.dist-info/WHEEL
kaiterra_async_client-1.1.0.dist-info/top_level.txt
kaiterra_async_client-1.1.0.dist-info/RECORD
