Metadata-Version: 2.1
Name: kaiterra-async-client
Version: 1.1.0
Summary: Kaiterra API Async Client
Home-page: https://github.com/Michsior14/python-kaiterra-async-client
License: MIT License
Classifier: Development Status :: 5 - Production/Stable
Classifier: Intended Audience :: Developers
Classifier: License :: OSI Approved :: MIT License
Classifier: Operating System :: OS Independent
Classifier: Programming Language :: Python :: 3.5
Classifier: Topic :: Software Development :: Libraries
Classifier: Topic :: Software Development :: Libraries :: Python Modules
Requires-Python: >=3.5
License-File: LICENSE
